预学习阶段/数字电路基础实验/lab1/dataflowModule/vsrc/reg1bit.v
module reg1bit (rst_n,d,q);
    input rst_n,d;
    output reg q;
    always @(*)
        if (rst_n == 1)
            q = 1'b0;  // Reset the output to 0
        else
            q = d;     // On clock edge, load the input data

endmodule

预学习阶段/数字电路基础实验/lab1/dataflowModule/vsrc/dump.vcd
$version Generated by VerilatedVcd $end
$timescale 1ps $end

 $scope module TOP $end
  $var wire  1 $ d $end
  $var wire  1 % q $end
  $var wire  1 # rst_n $end
  $scope module reg1bit $end
   $var wire  1 $ d $end
   $var wire  1 % q $end
   $var wire  1 # rst_n $end
  $upscope $end
 $upscope $end
$enddefinitions $end


#0
0#
1$
1%
#1
1#
0$
0%
#2
0#
1$
1%
#3
1#
0$
0%
#4
0#
1$
1%
#5
1#
0$
0%
#6
0#
1$
1%
#7
1#
0$
0%
#8
0#
1$
1%
#9
1#
0$
0%
