预学习阶段/数字电路基础实验/lab1/behaveModule/vsrcx/mux21c.v
module mux21c(a,b,s,y);
    input a,b,s;
    output reg y;

    always @ (*)
        if(s==0)
            y = a;
        else
            y = b;

endmodule

预学习阶段/数字电路基础实验/lab1/behaveModule/vsrcx/dump.vcd
$version Generated by VerilatedVcd $end
$timescale 1ps $end

 $scope module TOP $end
  $var wire  1 # a $end
  $var wire  1 $ b $end
  $var wire  1 % s $end
  $var wire  1 & y $end
  $scope module mux21c $end
   $var wire  1 # a $end
   $var wire  1 $ b $end
   $var wire  1 % s $end
   $var wire  1 & y $end
  $upscope $end
 $upscope $end
$enddefinitions $end


#0
0#
1$
0%
0&
#1
1%
1&
#2
0%
0&
#3
1%
1&
#4
0%
0&
#5
1%
1&
#6
0%
0&
#7
1%
1&
#8
0%
0&
#9
1%
1&
